PySide2-stubs/__init__.pyi
PySide2-stubs/Qt3DAnimation/_Qt3DAnimation.pyi
PySide2-stubs/Qt3DAnimation/__init__.pyi
PySide2-stubs/Qt3DAnimation/_functions.pyi
PySide2-stubs/Qt3DCore/_Qt3DCore.pyi
PySide2-stubs/Qt3DCore/__init__.pyi
PySide2-stubs/Qt3DCore/_functions.pyi
PySide2-stubs/Qt3DExtras/_Qt3DExtras.pyi
PySide2-stubs/Qt3DExtras/__init__.pyi
PySide2-stubs/Qt3DExtras/_functions.pyi
PySide2-stubs/Qt3DInput/_Qt3DInput.pyi
PySide2-stubs/Qt3DInput/__init__.pyi
PySide2-stubs/Qt3DInput/_functions.pyi
PySide2-stubs/Qt3DLogic/_Qt3DLogic.pyi
PySide2-stubs/Qt3DLogic/__init__.pyi
PySide2-stubs/Qt3DLogic/_functions.pyi
PySide2-stubs/Qt3DRender/_Qt3DRender.pyi
PySide2-stubs/Qt3DRender/__init__.pyi
PySide2-stubs/Qt3DRender/_functions.pyi
PySide2-stubs/QtAxContainer/_QAxBase.pyi
PySide2-stubs/QtAxContainer/_QAxObject.pyi
PySide2-stubs/QtAxContainer/_QAxScript.pyi
PySide2-stubs/QtAxContainer/_QAxScriptEngine.pyi
PySide2-stubs/QtAxContainer/_QAxScriptManager.pyi
PySide2-stubs/QtAxContainer/_QAxSelect.pyi
PySide2-stubs/QtAxContainer/_QAxWidget.pyi
PySide2-stubs/QtAxContainer/__init__.pyi
PySide2-stubs/QtAxContainer/_functions.pyi
PySide2-stubs/QtCharts/_QtCharts.pyi
PySide2-stubs/QtCharts/__init__.pyi
PySide2-stubs/QtCharts/_functions.pyi
PySide2-stubs/QtConcurrent/_QFutureQString.pyi
PySide2-stubs/QtConcurrent/_QFutureVoid.pyi
PySide2-stubs/QtConcurrent/_QFutureWatcherQString.pyi
PySide2-stubs/QtConcurrent/_QFutureWatcherVoid.pyi
PySide2-stubs/QtConcurrent/_QtConcurrent.pyi
PySide2-stubs/QtConcurrent/__init__.pyi
PySide2-stubs/QtConcurrent/_functions.pyi
PySide2-stubs/QtCore/_ClassInfo.pyi
PySide2-stubs/QtCore/_MetaFunction.pyi
PySide2-stubs/QtCore/_MetaSignal.pyi
PySide2-stubs/QtCore/_Property.pyi
PySide2-stubs/QtCore/_QAbstractAnimation.pyi
PySide2-stubs/QtCore/_QAbstractEventDispatcher.pyi
PySide2-stubs/QtCore/_QAbstractItemModel.pyi
PySide2-stubs/QtCore/_QAbstractListModel.pyi
PySide2-stubs/QtCore/_QAbstractNativeEventFilter.pyi
PySide2-stubs/QtCore/_QAbstractProxyModel.pyi
IceSpringPySideStubs_PySide2-1.3.1.dist-info/METADATA
IceSpringPySideStubs_PySide2-1.3.1.dist-info/WHEEL
IceSpringPySideStubs_PySide2-1.3.1.dist-info/top_level.txt
IceSpringPySideStubs_PySide2-1.3.1.dist-info/RECORD
